petminion/.gitignore
petminion/BallRecognizer.py
petminion/CV2Camera.py
petminion/Camera.py
petminion/ColorCorrector.py
petminion/Feeder.py
petminion/ImageRecognizer.py
petminion/MVTest.py
petminion/MastodonClient.py
petminion/PiCamera.py
petminion/ProcessedImage.py
petminion/PushoverClient.py
petminion/RateLimit.py
petminion/Recognizer.py
petminion/RedditClient.py
petminion/SocialMediaClient.py
petminion/Trainer.py
petminion/TrainingRule.py
petminion/VideoWriter.py
petminion/__init__.py
petminion/__main__.py
petminion/resources/__init__.py
petminion/resources/ref-pantone.jpg
petminion/resources/simcamera/README.md
petminion/resources/simcamera/__init__.py
petminion/resources/simcamera/crow1.jpg
petminion/resources/simcamera/crow2.jpg
petminion/resources/simcamera/crow3.jpg
petminion/resources/simcamera/crow4.jpg
petminion/util.py
petminion-0.2.1.dist-info/LICENSE
petminion-0.2.1.dist-info/METADATA
petminion-0.2.1.dist-info/WHEEL
petminion-0.2.1.dist-info/entry_points.txt
petminion-0.2.1.dist-info/RECORD
