Metadata-Version: 2.1
Name: petminion
Version: 0.2.1
Summary: An application/framework for automated training of animals
Home-page: https://petminion.org
License: GPL-3.0-or-later
Author: Kevin Hester
Author-email: kevinh@geeksville.com
Requires-Python: >=3.11,<4.0
Classifier: License :: OSI Approved :: GNU General Public License v3 or later (GPLv3+)
Classifier: Programming Language :: Python :: 3
Classifier: Programming Language :: Python :: 3.11
Classifier: Programming Language :: Python :: 3.12
Provides-Extra: docs
Requires-Dist: av (>=11.0.0,<12.0.0)
Requires-Dist: fpdf (>=1.7.2,<2.0.0)
Requires-Dist: imageai (>=3.0.3,<4.0.0)
Requires-Dist: imutils (>=0.5.4,<0.6.0)
Requires-Dist: jsonpickle (>=3.0.2,<4.0.0)
Requires-Dist: mastodon-py (>=1.8.1,<2.0.0)
Requires-Dist: numpy (>=1.26.2,<2.0.0)
Requires-Dist: opencv-python (>=4.8.1.78,<5.0.0.0)
Requires-Dist: paho-mqtt (>=1.6.1,<2.0.0)
Requires-Dist: pillow (>=10.1.0,<11.0.0)
Requires-Dist: platformdirs (==4.0.0)
Requires-Dist: praw (>=7.7.1,<8.0.0)
Requires-Dist: requests (>=2.31.0,<3.0.0)
Requires-Dist: scipy (>=1.12.0,<2.0.0)
Requires-Dist: torch (>=2.1.2,<3.0.0)
Requires-Dist: torchvision (>=0.16.2,<0.17.0)
Project-URL: Bug Tracker, https://github.com/geeksville/petminion/issues
Project-URL: Repository, https://github.com/petminion/petminion
